dash_basecomponent/__init__.py
dash_basecomponent/dash_basecomponent.py
dash_basecomponent-0.1.4.dist-info/LICENSE
dash_basecomponent-0.1.4.dist-info/METADATA
dash_basecomponent-0.1.4.dist-info/WHEEL
dash_basecomponent-0.1.4.dist-info/top_level.txt
dash_basecomponent-0.1.4.dist-info/RECORD
