Metadata-Version: 2.2
Name: dash_basecomponent
Version: 0.1.4
Summary: A base component library for Dash applications
Home-page: https://github.com/ribab/dash-basecomponent
Author: Richard Barella Jr.
Author-email: codingwithricky@gmail.com
Classifier: Development Status :: 3 - Alpha
Classifier: Intended Audience :: Developers
Classifier: Topic :: Software Development :: Libraries :: Application Frameworks
Classifier: Programming Language :: Python :: 3
Classifier: License :: OSI Approved :: MIT License
License-File: LICENSE
Requires-Dist: dash>=2.0.0
Dynamic: author
Dynamic: author-email
Dynamic: classifier
Dynamic: description
Dynamic: description-content-type
Dynamic: home-page
Dynamic: requires-dist
Dynamic: summary
